atomic_weights/__init__.py
atomic_weights/_decimal.py
atomic_weights/py.typed
atomic_weights-2023.0.0.dist-info/WHEEL
atomic_weights-2023.0.0.dist-info/METADATA
atomic_weights-2023.0.0.dist-info/RECORD
