Metadata-Version: 2.4
Name: atomic-weights
Version: 2023.0.0
Summary: Standard atomic weights of the elements
Author: Takumasa Nakamura
Author-email: Takumasa Nakamura <n.takumasa@gmail.com>
License-Expression: CC0-1.0
Classifier: Operating System :: OS Independent
Classifier: Programming Language :: Python :: 3
Classifier: Topic :: Scientific/Engineering :: Chemistry
Classifier: Topic :: Scientific/Engineering :: Physics
Requires-Python: >=3.8
Project-URL: source, https://github.com/n-takumasa/py-atomic-weights
